pltsave/__init__.py
pltsave/convert.py
pltsave/stuctures.py
pltsave-0.0.1.dist-info/LICENSE
pltsave-0.0.1.dist-info/METADATA
pltsave-0.0.1.dist-info/WHEEL
pltsave-0.0.1.dist-info/top_level.txt
pltsave-0.0.1.dist-info/RECORD
