Metadata-Version: 2.1
Name: pltsave
Version: 0.0.1
Summary: Data management library to save data and plots to hdf5 files
Home-page: https://github.com/kyrylo-gr/pltsave
Author: kyrylo
Author-email: cryo.paris.su@gmail.com
Classifier: Programming Language :: Python :: 3
Classifier: Operating System :: OS Independent
Requires-Python: >=3.8
License-File: LICENSE
Requires-Dist: numpy
Provides-Extra: dev
Requires-Dist: pytest ; extra == 'dev'
